praiag/__init__.py
praiag/main.py
praiag/settings.py
praiag-0.1.0.dist-info/METADATA
praiag-0.1.0.dist-info/WHEEL
praiag-0.1.0.dist-info/entry_points.txt
praiag-0.1.0.dist-info/RECORD
