Metadata-Version: 2.4
Name: praiag
Version: 0.1.0
Summary: This is a test for project.
Requires-Python: >=3.11
Requires-Dist: pydantic-settings>=2.7.1
Requires-Dist: pydantic>=2.10.5
